jam/__init__.py
jam/builder.html
jam/common.py
jam/dataset.py
jam/events.py
jam/execute.py
jam/items.py
jam/langs.py
jam/langs.sqlite
jam/server_classes.py
jam/sql.py
jam/wsgi.py
jam/wsgi_server.py
jam/admin/__init__.py
jam/admin/admin.py
jam/admin/builder.py
jam/admin/builder_structure.info
jam/admin/export_metadata.py
jam/admin/import_metadata.py
jam/admin/task.py
jam/css/admin.css
jam/css/admin.min.css
jam/css/bootstrap-amelia.css
jam/css/bootstrap-amelia.min.css
jam/css/bootstrap-cerulean.css
jam/css/bootstrap-cerulean.min.css
jam/css/bootstrap-cosmo.css
jam/css/bootstrap-cosmo.min.css
jam/css/bootstrap-flatly.css
jam/css/bootstrap-flatly.min.css
jam/css/bootstrap-journal.css
jam/css/bootstrap-journal.min.css
jam/css/bootstrap-modal.css
jam/css/bootstrap-modal.min.css
jam/css/bootstrap-readable.css
jam/css/bootstrap-readable.min.css
jam/css/bootstrap-responsive.css
jam/css/bootstrap-responsive.min.css
jam/css/bootstrap-slate.css
jam/css/bootstrap-slate.min.css
jam/css/bootstrap-spacelab.css
jam/css/bootstrap-spacelab.min.css
jam/css/bootstrap-united.css
jam/css/bootstrap-united.min.css
jam/css/bootstrap.css
jam/css/bootstrap.min.css
jam/css/datepicker.css
jam/css/datepicker.min.css
jam/css/jam.css
jam/css/jam.min.css
jam/css/jam12.css
jam/css/jam12.min.css
jam/db/__init__.py
jam/db/db_modules.py
jam/db/firebird.py
jam/db/mssql.py
jam/db/mysql.py
jam/db/oracle.py
jam/db/postgres.py
jam/db/sqlite.py
jam/img/glyphicons-halflings-white.png
jam/img/glyphicons-halflings.png
jam/img/j.ico
jam/img/j.png
jam/img/placeholder.png
jam/js/admin.js
jam/js/admin.min.js
jam/js/bootstrap-datepicker.js
jam/js/bootstrap-datepicker.min.js
jam/js/bootstrap-modal.js
jam/js/bootstrap-modal.min.js
jam/js/bootstrap-modalmanager.js
jam/js/bootstrap-modalmanager.min.js
jam/js/bootstrap.js
jam/js/bootstrap.min.js
jam/js/jam.js
jam/js/jam.min.js
jam/js/jquery.js
jam/js/jquery.maskedinput.js
jam/js/jquery.maskedinput.min.js
jam/js/jquery.min.js
jam/js/md5.js
jam/js/md5.min.js
jam.py_v5-5.5.4.dist-info/AUTHORS
jam.py_v5-5.5.4.dist-info/LICENSE
jam.py_v5-5.5.4.dist-info/METADATA
jam.py_v5-5.5.4.dist-info/WHEEL
jam.py_v5-5.5.4.dist-info/top_level.txt
jam.py_v5-5.5.4.dist-info/RECORD
